{"frames": {

"BaseSymbolBoomEffect_0000.png":
{
	"frame": {"x":0,"y":0,"w":400,"h":400},
	"rotated": false,
	"trimmed": false,
	"spriteSourceSize": {"x":0,"y":0,"w":400,"h":400},
	"sourceSize": {"w":400,"h":400}
},
"BaseSymbolBoomEffect_0001.png":
{
	"frame": {"x":400,"y":0,"w":400,"h":400},
	"rotated": false,
	"trimmed": false,
	"spriteSourceSize": {"x":0,"y":0,"w":400,"h":400},
	"sourceSize": {"w":400,"h":400}
},
"BaseSymbolBoomEffect_0002.png":
{
	"frame": {"x":800,"y":0,"w":400,"h":400},
	"rotated": false,
	"trimmed": false,
	"spriteSourceSize": {"x":0,"y":0,"w":400,"h":400},
	"sourceSize": {"w":400,"h":400}
},
"BaseSymbolBoomEffect_0003.png":
{
	"frame": {"x":1200,"y":0,"w":400,"h":400},
	"rotated": false,
	"trimmed": false,
	"spriteSourceSize": {"x":0,"y":0,"w":400,"h":400},
	"sourceSize": {"w":400,"h":400}
},
"BaseSymbolBoomEffect_0004.png":
{
	"frame": {"x":1600,"y":0,"w":400,"h":400},
	"rotated": false,
	"trimmed": false,
	"spriteSourceSize": {"x":0,"y":0,"w":400,"h":400},
	"sourceSize": {"w":400,"h":400}
},
"BaseSymbolBoomEffect_0005.png":
{
	"frame": {"x":0,"y":400,"w":400,"h":400},
	"rotated": false,
	"trimmed": false,
	"spriteSourceSize": {"x":0,"y":0,"w":400,"h":400},
	"sourceSize": {"w":400,"h":400}
},
"BaseSymbolBoomEffect_0006.png":
{
	"frame": {"x":400,"y":400,"w":400,"h":400},
	"rotated": false,
	"trimmed": false,
	"spriteSourceSize": {"x":0,"y":0,"w":400,"h":400},
	"sourceSize": {"w":400,"h":400}
},
"BaseSymbolBoomEffect_0007.png":
{
	"frame": {"x":800,"y":400,"w":400,"h":400},
	"rotated": false,
	"trimmed": false,
	"spriteSourceSize": {"x":0,"y":0,"w":400,"h":400},
	"sourceSize": {"w":400,"h":400}
},
"BaseSymbolBoomEffect_0008.png":
{
	"frame": {"x":1200,"y":400,"w":400,"h":400},
	"rotated": false,
	"trimmed": false,
	"spriteSourceSize": {"x":0,"y":0,"w":400,"h":400},
	"sourceSize": {"w":400,"h":400}
},
"BaseSymbolBoomEffect_0009.png":
{
	"frame": {"x":1600,"y":400,"w":400,"h":400},
	"rotated": false,
	"trimmed": false,
	"spriteSourceSize": {"x":0,"y":0,"w":400,"h":400},
	"sourceSize": {"w":400,"h":400}
},
"BaseSymbolBoomEffect_0010.png":
{
	"frame": {"x":0,"y":800,"w":400,"h":400},
	"rotated": false,
	"trimmed": false,
	"spriteSourceSize": {"x":0,"y":0,"w":400,"h":400},
	"sourceSize": {"w":400,"h":400}
},
"BaseSymbolBoomEffect_0011.png":
{
	"frame": {"x":400,"y":800,"w":400,"h":400},
	"rotated": false,
	"trimmed": false,
	"spriteSourceSize": {"x":0,"y":0,"w":400,"h":400},
	"sourceSize": {"w":400,"h":400}
},
"BaseSymbolBoomEffect_0012.png":
{
	"frame": {"x":800,"y":800,"w":400,"h":400},
	"rotated": false,
	"trimmed": false,
	"spriteSourceSize": {"x":0,"y":0,"w":400,"h":400},
	"sourceSize": {"w":400,"h":400}
},
"BaseSymbolBoomEffect_0013.png":
{
	"frame": {"x":1200,"y":800,"w":400,"h":400},
	"rotated": false,
	"trimmed": false,
	"spriteSourceSize": {"x":0,"y":0,"w":400,"h":400},
	"sourceSize": {"w":400,"h":400}
},
"BaseSymbolBoomEffect_0014.png":
{
	"frame": {"x":1600,"y":800,"w":400,"h":400},
	"rotated": false,
	"trimmed": false,
	"spriteSourceSize": {"x":0,"y":0,"w":400,"h":400},
	"sourceSize": {"w":400,"h":400}
},
"BaseSymbolBoomEffect_0015.png":
{
	"frame": {"x":0,"y":1200,"w":400,"h":400},
	"rotated": false,
	"trimmed": false,
	"spriteSourceSize": {"x":0,"y":0,"w":400,"h":400},
	"sourceSize": {"w":400,"h":400}
},
"BaseSymbolBoomEffect_0016.png":
{
	"frame": {"x":400,"y":1200,"w":400,"h":400},
	"rotated": false,
	"trimmed": false,
	"spriteSourceSize": {"x":0,"y":0,"w":400,"h":400},
	"sourceSize": {"w":400,"h":400}
},
"BaseSymbolBoomEffect_0017.png":
{
	"frame": {"x":800,"y":1200,"w":400,"h":400},
	"rotated": false,
	"trimmed": false,
	"spriteSourceSize": {"x":0,"y":0,"w":400,"h":400},
	"sourceSize": {"w":400,"h":400}
},
"BaseSymbolBoomEffect_0018.png":
{
	"frame": {"x":1200,"y":1200,"w":400,"h":400},
	"rotated": false,
	"trimmed": false,
	"spriteSourceSize": {"x":0,"y":0,"w":400,"h":400},
	"sourceSize": {"w":400,"h":400}
},
"BaseSymbolBoomEffect_0019.png":
{
	"frame": {"x":1600,"y":1200,"w":400,"h":400},
	"rotated": false,
	"trimmed": false,
	"spriteSourceSize": {"x":0,"y":0,"w":400,"h":400},
	"sourceSize": {"w":400,"h":400}
},
"BaseSymbolBoomEffect_0020.png":
{
	"frame": {"x":0,"y":1600,"w":400,"h":400},
	"rotated": false,
	"trimmed": false,
	"spriteSourceSize": {"x":0,"y":0,"w":400,"h":400},
	"sourceSize": {"w":400,"h":400}
},
"BaseSymbolBoomEffect_0021.png":
{
	"frame": {"x":400,"y":1600,"w":400,"h":400},
	"rotated": false,
	"trimmed": false,
	"spriteSourceSize": {"x":0,"y":0,"w":400,"h":400},
	"sourceSize": {"w":400,"h":400}
},
"BaseSymbolBoomEffect_0022.png":
{
	"frame": {"x":800,"y":1600,"w":400,"h":400},
	"rotated": false,
	"trimmed": false,
	"spriteSourceSize": {"x":0,"y":0,"w":400,"h":400},
	"sourceSize": {"w":400,"h":400}
}},
"animations": {
	"BaseSymbolBoomEffect": ["BaseSymbolBoomEffect_0000.png","BaseSymbolBoomEffect_0001.png","BaseSymbolBoomEffect_0002.png","BaseSymbolBoomEffect_0003.png","BaseSymbolBoomEffect_0004.png","BaseSymbolBoomEffect_0005.png","BaseSymbolBoomEffect_0006.png","BaseSymbolBoomEffect_0007.png","BaseSymbolBoomEffect_0008.png","BaseSymbolBoomEffect_0009.png","BaseSymbolBoomEffect_0010.png","BaseSymbolBoomEffect_0011.png","BaseSymbolBoomEffect_0012.png","BaseSymbolBoomEffect_0013.png","BaseSymbolBoomEffect_0014.png","BaseSymbolBoomEffect_0015.png","BaseSymbolBoomEffect_0016.png","BaseSymbolBoomEffect_0017.png","BaseSymbolBoomEffect_0018.png","BaseSymbolBoomEffect_0019.png","BaseSymbolBoomEffect_0020.png","BaseSymbolBoomEffect_0021.png","BaseSymbolBoomEffect_0022.png"]
},
"meta": {
	"app": "https://www.codeandweb.com/texturepacker",
	"version": "1.0",
	"image": "BaseSymbolBoomEffect.png",
	"format": "RGBA8888",
	"size": {"w":2000,"h":2000},
	"scale": "1",
	"smartupdate": "$TexturePacker:SmartUpdate:785f6a26cbf699095d38c9ec791f0fd1:133acb46408ef7ae0b6b6c36acdf3e04:ec2582743013e2e5a826e5370d8ca7ad$"
}
}
